pcdsdevices/__init__.py
pcdsdevices/_html.py
pcdsdevices/_version.py
pcdsdevices/analog_signals.py
pcdsdevices/atm.py
pcdsdevices/attenuator.py
pcdsdevices/beam_stats.py
pcdsdevices/ccm.py
pcdsdevices/component.py
pcdsdevices/crix_motion.py
pcdsdevices/custom_units.py
pcdsdevices/cvmi_bootstrap.py
pcdsdevices/cvmi_motion.py
pcdsdevices/dc_devices.py
pcdsdevices/dccm.py
pcdsdevices/delay_generator.py
pcdsdevices/device.py
pcdsdevices/device_types.py
pcdsdevices/digital_signals.py
pcdsdevices/digitizers.py
pcdsdevices/doc_stubs.py
pcdsdevices/dream_motion.py
pcdsdevices/energy_monitor.py
pcdsdevices/epics_motor.py
pcdsdevices/eps.py
pcdsdevices/evr.py
pcdsdevices/example.py
pcdsdevices/fms.py
pcdsdevices/gauge.py
pcdsdevices/gbs.py
pcdsdevices/gon.py
pcdsdevices/inout.py
pcdsdevices/interface.py
pcdsdevices/ipm.py
pcdsdevices/jet.py
pcdsdevices/keithley.py
pcdsdevices/lakeshore.py
pcdsdevices/lamp_motion.py
pcdsdevices/lens.py
pcdsdevices/lic.py
pcdsdevices/lic_2d_tmo.py
pcdsdevices/light_control.py
pcdsdevices/lodcm.py
pcdsdevices/lxe.py
pcdsdevices/make_ophyd_device.py
pcdsdevices/mirror.py
pcdsdevices/movablestand.py
pcdsdevices/mpod.py
pcdsdevices/mpod_apalis.py
pcdsdevices/mps.py
pcdsdevices/mrco_motion.py
pcdsdevices/mv_interface.py
pcdsdevices/pc.py
pcdsdevices/pdu.py
pcdsdevices/piezo.py
pcdsdevices/pim.py
pcdsdevices/pmps.py
pcdsdevices/pneumatic.py
pcdsdevices/positioner.py
pcdsdevices/pseudopos.py
pcdsdevices/pulsepicker.py
pcdsdevices/pump.py
pcdsdevices/pv_positioner.py
pcdsdevices/qadc.py
pcdsdevices/radiation.py
pcdsdevices/ref.py
pcdsdevices/registry.py
pcdsdevices/rs_powersupply.py
pcdsdevices/rtds_ebd.py
pcdsdevices/sample_delivery.py
pcdsdevices/sensors.py
pcdsdevices/sequencer.py
pcdsdevices/signal.py
pcdsdevices/sim.py
pcdsdevices/slits.py
pcdsdevices/smarpod.py
pcdsdevices/spectrometer.py
pcdsdevices/sqr1.py
pcdsdevices/state.py
pcdsdevices/stopper.py
pcdsdevices/sxr_test_absorber.py
pcdsdevices/tags.py
pcdsdevices/targets.py
pcdsdevices-10.0.0.dist-info/licenses/AUTHORS.rst
pcdsdevices-10.0.0.dist-info/licenses/LICENSE.md
pcdsdevices-10.0.0.dist-info/METADATA
pcdsdevices-10.0.0.dist-info/WHEEL
pcdsdevices-10.0.0.dist-info/entry_points.txt
pcdsdevices-10.0.0.dist-info/top_level.txt
pcdsdevices-10.0.0.dist-info/RECORD
