Metadata-Version: 2.4
Name: pcdsdevices
Version: 10.0.0
Summary: Ophyd Device definitions for LCLS Beamline components
Author: SLAC National Accelerator Laboratory
License: Copyright (c) 2023, The Board of Trustees of the Leland Stanford Junior
Classifier: Programming Language :: Python :: 3
Requires-Python: >=3.9
License-File: LICENSE.md
License-File: AUTHORS.rst
Requires-Dist: bluesky>=1.6.4
Requires-Dist: happi
Requires-Dist: jsonschema
Requires-Dist: lightpath>=1.0.5
Requires-Dist: numpy
Requires-Dist: ophyd>=1.7.0
Requires-Dist: pcdscalc>=0.2.0
Requires-Dist: pcdsutils>=0.4.0
Requires-Dist: prettytable
Requires-Dist: pyepics<3.5.8,>=3.4.2
Requires-Dist: pytmc>=2.7.0
Requires-Dist: pyyaml
Requires-Dist: schema
Requires-Dist: scipy
Requires-Dist: sympy
Provides-Extra: test
Requires-Dist: pytest; extra == "test"
Requires-Dist: pytest-timeout; extra == "test"
Requires-Dist: matplotlib; extra == "test"
Requires-Dist: typhos; extra == "test"
Provides-Extra: doc
Requires-Dist: docs-versions-menu; extra == "doc"
Requires-Dist: sphinx>=3.3.1; extra == "doc"
Requires-Dist: sphinx_rtd_theme; extra == "doc"
Requires-Dist: whatrecord; extra == "doc"
Requires-Dist: ipython; extra == "doc"
Requires-Dist: sphinxcontrib-jquery; extra == "doc"
Requires-Dist: PyQt5; extra == "doc"
Dynamic: license-file
